Metadata-Version: 1.0
Name: python-figures
Version: 1.0
Summary: 😀 Can use unicode symbols on any OS!
Home-page: https://github.com/h4wldev/python-figures
Author: Junho Kim
Author-email: h4wldev@gmail.com
License: MIT
Platform: UNKNOWN
